sigmaflow/__init__.py
sigmaflow/cmd.py
sigmaflow/log.py
sigmaflow/utils.py
sigmaflow/version.py
sigmaflow/blocks/__init__.py
sigmaflow/blocks/base.py
sigmaflow/blocks/block_browser.py
sigmaflow/blocks/block_llm.py
sigmaflow/blocks/block_rag.py
sigmaflow/blocks/block_search.py
sigmaflow/clients/__init__.py
sigmaflow/clients/llm.py
sigmaflow/clients/llm_lmdeploy.py
sigmaflow/clients/llm_mlx.py
sigmaflow/clients/llm_mlx_batch.py
sigmaflow/clients/llm_ollama.py
sigmaflow/clients/llm_openai.py
sigmaflow/clients/llm_pulse.py
sigmaflow/clients/llm_torch.py
sigmaflow/clients/llm_vllm.py
sigmaflow/clients/rag_http.py
sigmaflow/clients/rag_json.py
sigmaflow/clients/search_bing.py
sigmaflow/managers/__init__.py
sigmaflow/managers/pipeline_manager.py
sigmaflow/managers/prompt_manager.py
sigmaflow/nodes/__init__.py
sigmaflow/nodes/base.py
sigmaflow/nodes/constant.py
sigmaflow/nodes/node.py
sigmaflow/nodes/node_api.py
sigmaflow/nodes/node_branch.py
sigmaflow/nodes/node_browser.py
sigmaflow/nodes/node_code.py
sigmaflow/nodes/node_config.py
sigmaflow/nodes/node_database.py
sigmaflow/nodes/node_exit.py
sigmaflow/nodes/node_file.py
sigmaflow/nodes/node_llm.py
sigmaflow/nodes/node_loop.py
sigmaflow/nodes/node_mcp.py
sigmaflow/nodes/node_rag.py
sigmaflow/nodes/node_subgraph.py
sigmaflow/nodes/node_value.py
sigmaflow/nodes/node_web.py
sigmaflow/pipeline/__init__.py
sigmaflow/pipeline/graph.py
sigmaflow/pipeline/pipegraph.py
sigmaflow/pipeline/pipeline.py
sigmaflow/prompts/__init__.py
sigmaflow/prompts/branch_node_prompt.py
sigmaflow/prompts/prompt.py
sigmaflow/server/__init__.py
sigmaflow/server/api.py
sigmaflow/server/constant.py
sigmaflow/server/main.py
sigmaflow/server/models.json
sigmaflow/server/object_info.json
sigmaflow/server/sigmaflow.json
sigmaflow/server/task.py
sigmaflow/server/workspace.py
sigmaflow/server/comfyui/dist/index.html
sigmaflow/server/comfyui/dist/materialdesignicons.min.css
sigmaflow/server/comfyui/dist/assets/ABCROMExtended-BlackItalic-B3Ak1JoQ.woff
sigmaflow-0.0.60.dist-info/licenses/LICENSE
sigmaflow-0.0.60.dist-info/METADATA
sigmaflow-0.0.60.dist-info/WHEEL
sigmaflow-0.0.60.dist-info/entry_points.txt
sigmaflow-0.0.60.dist-info/top_level.txt
sigmaflow-0.0.60.dist-info/RECORD
