Metadata-Version: 2.4
Name: SigmaFlow
Version: 0.0.60
Summary: SigmaFlow is a Python package designed to optimize the performance of task-flow related to LLMs/MLLMs or Multi-agent
Author-email: Kangkun Mao <maokangkun@pjlab.org.cn>
License-Expression: MIT
Project-URL: Homepage, https://sigmaflows.github.io/
Project-URL: Repository, https://github.com/maokangkun/SigmaFlow
Classifier: Typing :: Typed
Classifier: Intended Audience :: Developers
Classifier: Programming Language :: Python :: 3
Classifier: Programming Language :: Python :: 3.10
Classifier: Programming Language :: Python :: 3.11
Classifier: Programming Language :: Python :: 3.12
Classifier: Programming Language :: Python :: 3.13
Classifier: Programming Language :: Python :: 3.14
Classifier: Operating System :: OS Independent
Classifier: Topic :: Software Development :: Libraries :: Python Modules
Requires-Python: >=3.10
License-File: LICENSE
Requires-Dist: rich
Requires-Dist: openai
Requires-Dist: dotenv
Requires-Dist: ollama
Requires-Dist: pandas
Requires-Dist: Pillow
Requires-Dist: fastapi
Requires-Dist: requests
Requires-Dist: packaging
Requires-Dist: uvicorn[standard]
Provides-Extra: all
Requires-Dist: pymupdf4llm; extra == "all"
Dynamic: license-file
